.coveragerc
.mailmap
.stestr.conf
AUTHORS
CONTRIBUTING.rst
ChangeLog
HACKING.rst
LICENSE
README.rst
babel.cfg
requirements.txt
setup.cfg
setup.py
test-requirements.txt
tox.ini
doc/source/conf.py
doc/source/index.rst
doc/source/readme.rst
doc/source/admin/index.rst
doc/source/cli/index.rst
doc/source/configuration/index.rst
doc/source/contributor/contributing.rst
doc/source/contributor/index.rst
doc/source/install/common_configure.rst
doc/source/install/common_prerequisites.rst
doc/source/install/get_started.rst
doc/source/install/index.rst
doc/source/install/install-obs.rst
doc/source/install/install-rdo.rst
doc/source/install/install-ubuntu.rst
doc/source/install/install.rst
doc/source/install/next-steps.rst
doc/source/install/verify.rst
doc/source/library/index.rst
doc/source/reference/index.rst
doc/source/user/index.rst
os_vif_bigswitch/__init__.py
os_vif_bigswitch.egg-info/PKG-INFO
os_vif_bigswitch.egg-info/SOURCES.txt
os_vif_bigswitch.egg-info/dependency_links.txt
os_vif_bigswitch.egg-info/entry_points.txt
os_vif_bigswitch.egg-info/not-zip-safe
os_vif_bigswitch.egg-info/pbr.json
os_vif_bigswitch.egg-info/requires.txt
os_vif_bigswitch.egg-info/top_level.txt
os_vif_bigswitch/tests/__init__.py
os_vif_bigswitch/tests/base.py
os_vif_bigswitch/tests/test_os_vif_bigswitch.py
os_vif_bigswitch/vif_plug_ivs/__init__.py
os_vif_bigswitch/vif_plug_ivs/exception.py
os_vif_bigswitch/vif_plug_ivs/i18n.py
os_vif_bigswitch/vif_plug_ivs/ivs.py
os_vif_bigswitch/vif_plug_ivs/linux_net.py
os_vif_bigswitch/vif_plug_ivs/privsep.py
releasenotes/notes/.placeholder
releasenotes/source/conf.py
releasenotes/source/index.rst
releasenotes/source/unreleased.rst
releasenotes/source/_static/.placeholder
releasenotes/source/_templates/.placeholder