Metadata-Version: 1.1
Name: os-vif-bigswitch
Version: 12.0.0
Summary: Neutron OS-VIF plugin for Big Switch Networks SWL-VX
Home-page: http://www.openstack.org/
Author: OpenStack
Author-email: openstack-dev@lists.openstack.org
License: UNKNOWN
Platform: UNKNOWN
Classifier: Environment :: OpenStack
Classifier: Intended Audience :: Information Technology
Classifier: Intended Audience :: System Administrators
Classifier: License :: OSI Approved :: Apache Software License
Classifier: Operating System :: POSIX :: Linux
Classifier: Programming Language :: Python
Classifier: Programming Language :: Python :: 2
Classifier: Programming Language :: Python :: 2.7
Classifier: Programming Language :: Python :: 3
Classifier: Programming Language :: Python :: 3.5
